<?xml version="1.0" encoding="UTF-8"?>
<classDecl xmlns="http://www.tei-c.org/ns/1.0">
  <!-- *******************************    Object        ****************************** -->
  <taxonomy xml:id="USEp-genre">
      <category xml:id="slab">
         <catDesc>Slab</catDesc>
      </category>
      <category xml:id="tablet">
         <catDesc>Tablet</catDesc>
      </category>
      <category xml:id="stele">
         <catDesc>Stele</catDesc>
      </category>
      <category xml:id="cippus">
         <catDesc>Cippus</catDesc>
      </category>
      <!-- separator -->
      <category xml:id="altar">
         <catDesc>Altar</catDesc>
      </category>
      <category xml:id="base">
         <catDesc>Base</catDesc>
      </category>
      <category xml:id="ash_urn">
         <catDesc>Ash Urn</catDesc>
      </category>
      <category xml:id="sarcophagus">
         <catDesc>Sarcophagus</catDesc>
      </category>
      <!-- separator -->
      <category xml:id="sculpture">
         <catDesc>Sculpture</catDesc>
      </category>
      <category xml:id="arch_element">
         <catDesc>Architectural Element</catDesc>
      </category>
      <category xml:id="furniture">
         <catDesc>Furniture</catDesc>
      </category>
      <!-- separator -->
      <category xml:id="instrumentum">
         <catDesc>Instrumentum</catDesc>
         <category xml:id="instrumentum.brick">
            <catDesc>Brick</catDesc>
         </category>
         <category xml:id="instrumentum.container">
            <catDesc>Container</catDesc>
            <category xml:id="instrumentum.container.amphora">
               <catDesc>Amphora</catDesc>
            </category>
            <category xml:id="instrumentum.container.vase">
               <catDesc>Vase</catDesc>
            </category>
            <category xml:id="instrumentum.container.other">
               <catDesc>Other</catDesc>
            </category>
         </category>
         <category xml:id="instrumentum.lamp">
            <catDesc>Lamp</catDesc>
         </category>
         <category xml:id="instrumentum.armor">
            <catDesc>Armor</catDesc>
         </category>
         <category xml:id="instrumentum.jewelry">
            <catDesc>Jewelry</catDesc>
         </category>
         <category xml:id="instrumentum.tableware">
            <catDesc>Tableware</catDesc>
         </category>
         <category xml:id="instrumentum.tessera">
            <catDesc>Tag / Token (Tessera)</catDesc>
         </category>
         <category xml:id="instrumentum.toiletries">
            <catDesc>Toiletries</catDesc>
         </category>
         <category xml:id="instrumentum.other">
            <catDesc>Other</catDesc>
         </category>
      </category>
      <!-- separator -->
      <category xml:id="fragment">
         <catDesc>Fragment</catDesc>
      </category>
      <category xml:id="object_other">
         <catDesc>Other</catDesc>
      </category>
      <category xml:id="object_unknown">
         <catDesc>Unknown</catDesc>
      </category>
  </taxonomy>
  <!-- *******************************     Materials        ****************************** -->
  <taxonomy xml:id="USEp-materials">
      <category xml:id="stone">
         <catDesc>Stone</catDesc>
         <category xml:id="stone.marble">
            <catDesc>Marble</catDesc>
         </category>
         <category xml:id="stone.limestone">
            <catDesc>Limestone</catDesc>
         </category>
         <category xml:id="stone.travertine">
            <catDesc>Travertine</catDesc>
         </category>
         <category xml:id="stone.granite">
            <catDesc>Granite</catDesc>
         </category>
         <category xml:id="stone.tufa">
            <catDesc>Tufa</catDesc>
         </category>
         <category xml:id="stone.other">
            <catDesc>Other</catDesc>
         </category>
         <category xml:id="stone.unknown">
            <catDesc>Unknown</catDesc>
         </category>
      </category>
      <category xml:id="clay">
         <catDesc>Clay</catDesc>
         <category xml:id="clay.brick">
            <catDesc>Brick</catDesc>
         </category>
         <category xml:id="clay.terracotta">
            <catDesc>Terracotta</catDesc>
         </category>
         <category xml:id="clay.ceramic">
            <catDesc>Ceramic (glazed)</catDesc>
         </category>
      </category>
      <category xml:id="metal">
         <catDesc>Metal</catDesc>
         <category xml:id="metal.lead">
            <catDesc>Lead</catDesc>
         </category>
         <category xml:id="metal.bronze">
            <catDesc>Bronze, Copper Alloy</catDesc>
         </category>
         <category xml:id="metal.gold">
            <catDesc>Gold</catDesc>
         </category>
         <category xml:id="metal.silver">
            <catDesc>Silver</catDesc>
         </category>
         <category xml:id="metal.other">
            <catDesc>Other</catDesc>
         </category>
         <category xml:id="metal.unknown">
            <catDesc>Unknown</catDesc>
         </category>
      </category>
      <!-- separator -->
      <category xml:id="plaster">
         <catDesc>Plaster</catDesc>
      </category>
      <category xml:id="glass">
         <catDesc>Glass</catDesc>
      </category>
      <category xml:id="wood">
         <catDesc>Wood</catDesc>
      </category>
      <category xml:id="bone">
         <catDesc>Bone</catDesc>
      </category>
      <category xml:id="material_other">
         <catDesc>Other</catDesc>
      </category>
  </taxonomy>
  <!-- *******************************     Text Genre        ****************************** -->
  <taxonomy xml:id="USEp-form">
      <category xml:id="funerary">
         <catDesc>Funerary</catDesc>
         <category xml:id="funerary.epitaph">
            <catDesc>Epitaph</catDesc>
         </category>
         <category xml:id="funerary.iura">
            <catDesc>Iura Sepulcrorum</catDesc>
         </category>
         <category xml:id="funerary.other">
            <catDesc>Other</catDesc>
         </category>
      </category>
      <category xml:id="dedicatory">
         <catDesc>Dedicatory</catDesc>
      </category>
      <category xml:id="honorific">
         <catDesc>Honorific</catDesc>
         <category xml:id="honorific.acclamation">
            <catDesc>Acclamation</catDesc>
         </category>
         <category xml:id="honorific.other">
            <catDesc>Other</catDesc>
         </category>
      </category>
      <!-- separator line -->
      <category xml:id="building">
         <catDesc>Building</catDesc>
      </category>
      <category xml:id="document">
         <catDesc>Document</catDesc>
         <category xml:id="document.private">
            <catDesc>Private</catDesc>
         </category>
         <category xml:id="document.public">
            <catDesc>Public</catDesc>
         </category>
      </category>
      <category xml:id="fasti">
         <catDesc>Fasti</catDesc>
         <category xml:id="fasti.list">
            <catDesc>List</catDesc>
         </category>
         <category xml:id="fasti.calendar">
            <catDesc>Calendar</catDesc>
         </category>
      </category>
      <category xml:id="place_marker">
         <catDesc>Place Marker</catDesc>
         <category xml:id="place_marker.boundary">
            <catDesc>Boundary marker</catDesc>
         </category>
         <category xml:id="place_marker.milestone">
            <catDesc>Milestone</catDesc>
         </category>
         <category xml:id="place_marker.other">
            <catDesc>Other</catDesc>
         </category>
      </category>
      <!-- separator line -->
      <category xml:id="magic">
         <catDesc>Magic</catDesc>
         <category xml:id="magic.defixio">
            <catDesc>Defixio</catDesc>
         </category>
         <category xml:id="magic.other">
            <catDesc>Other</catDesc>
         </category>
      </category>
      <category xml:id="verse">
         <catDesc>Verse</catDesc>
      </category>
      <category xml:id="agonistic_ludic">
         <catDesc>Agonistic / Ludic</catDesc>
      </category>
      <category xml:id="label">
         <catDesc>Label</catDesc>
      </category>
      <!-- separator line -->
      <category xml:id="text_other">
         <catDesc>Other</catDesc>
      </category>
      <category xml:id="text_unknown">
         <catDesc>Unknown</catDesc>
      </category>
  </taxonomy>
  <!-- *******************************     Preservation        ****************************** -->
  <taxonomy xml:id="USEp-preservation">
      <category xml:id="complete">
         <catDesc>Complete</catDesc>
         <category xml:id="complete.broken">
            <catDesc>Broken</catDesc>
         </category>
         <category xml:id="complete.intact">
            <catDesc>Intact</catDesc>
         </category>
      </category>
      <category xml:id="fragment.single">
         <catDesc>Fragment</catDesc>
      </category>
      <category xml:id="fragments">
         <catDesc>Fragments</catDesc>
         <category xml:id="fragments.contig">
            <catDesc>Contiguous</catDesc>
         </category>
         <category xml:id="fragments.non_contig">
            <catDesc>Non-Contiguous</catDesc>
         </category>
      </category>
  </taxonomy>
  <!-- *******************************     Writing        ****************************** -->
  <taxonomy xml:id="USEp-writing">
      <category xml:id="impressed">
         <catDesc>Impressed</catDesc>
         <category xml:id="impressed.inscribed">
            <catDesc>Inscribed</catDesc>
            <category xml:id="impressed.inscribed.chiseled">
               <catDesc>Chiseled</catDesc>
            </category>
            <category xml:id="impressed.inscribed.etched">
               <catDesc>Etched (with a sharp point)</catDesc>
            </category>
            <category xml:id="impressed.inscribed.carved">
               <catDesc>Carved</catDesc>
            </category>
         </category>
         <category xml:id="impressed.troughs">
            <catDesc>In Troughs</catDesc>
         </category>
         <category xml:id="impressed.points">
            <catDesc>In Points (chasing)</catDesc>
         </category>
         <category xml:id="impressed.other">
            <catDesc>Other</catDesc>
         </category>
      </category>
      <!-- separator -->
      <category xml:id="protruding">
         <catDesc>Protruding</catDesc>
         <category xml:id="protruding.applied">
            <catDesc>Applied</catDesc>
         </category>
         <category xml:id="protruding.molded">
            <catDesc>Molded</catDesc>
         </category>
         <category xml:id="protruding.relief">
            <catDesc>In Relief (cut)</catDesc>
         </category>
         <category xml:id="protruding.points">
            <catDesc>In Points (repouss)</catDesc>
         </category>
      </category>
      <category xml:id="painted">
         <catDesc>Painted</catDesc>
         <category xml:id="painted.brush">
            <catDesc>With Brush</catDesc>
         </category>
         <category xml:id="painted.other">
            <catDesc>With Other</catDesc>
         </category>
      </category>
      <category xml:id="inset">
         <catDesc>Inset</catDesc>
         <category xml:id="inset.mosaic">
            <catDesc>Mosaic</catDesc>
         </category>
         <category xml:id="inset.inlaid">
            <catDesc>Inlaid</catDesc>
         </category>
      </category>
      <category xml:id="stamped">
         <catDesc>Stamped</catDesc>
         <category xml:id="stamped.impressed">
            <catDesc>Impressed</catDesc>
         </category>
         <category xml:id="stamped.relief">
            <catDesc>In Relief</catDesc>
         </category>
      </category>
  </taxonomy>
</classDecl>
